raudio_bot/__init__.py
raudio_bot/__main__.py
raudio_bot/bot.py
raudio_bot/config.py
raudio_bot/modules/BasicCommands.py
raudio_bot/modules/Music.py
raudio_bot/modules/__init__.py
raudio_bot-0.1.0rc1.dist-info/LICENSE
raudio_bot-0.1.0rc1.dist-info/METADATA
raudio_bot-0.1.0rc1.dist-info/WHEEL
raudio_bot-0.1.0rc1.dist-info/top_level.txt
raudio_bot-0.1.0rc1.dist-info/RECORD
