Metadata-Version: 2.1
Name: raudio-bot
Version: 0.1.0rc1
Summary: Self-hosted music streaming discord bot
Home-page: https://raudio-project.github.io
Author: Raudio Project
Author-email: ndlug@nd.edu
License: UNKNOWN
Platform: UNKNOWN
Classifier: Programming Language :: Python :: 3
Classifier: License :: OSI Approved :: GNU General Public License v3 (GPLv3)
Requires-Python: >=3.7
License-File: LICENSE
Requires-Dist: py-cord[voice] (==1.7.3)
Requires-Dist: python-dotenv (==0.20.0)
Requires-Dist: requests (==2.27.1)
